decred/__init__.py
decred/btc/nets/__init__.py
decred/btc/nets/mainnet.py
decred/btc/nets/regtest.py
decred/btc/nets/simnet.py
decred/btc/nets/testnet.py
decred/crypto/__init__.py
decred/crypto/crypto.py
decred/crypto/gcs.py
decred/crypto/mnemonic.py
decred/crypto/opcode.py
decred/crypto/rando.py
decred/crypto/secp256k1/__init__.py
decred/crypto/secp256k1/bytepoints.py
decred/crypto/secp256k1/curve.py
decred/crypto/secp256k1/field.pxd
decred/crypto/secp256k1/field.py
decred/dcr/__init__.py
decred/dcr/account.py
decred/dcr/addrlib.py
decred/dcr/agenda.py
decred/dcr/assets/favicon-32x32.png
decred/dcr/assets/logo.svg
decred/dcr/blockchain.py
decred/dcr/constants.py
decred/dcr/dcrdata.py
decred/dcr/nets/__init__.py
decred/dcr/nets/mainnet.py
decred/dcr/nets/simnet.py
decred/dcr/nets/testnet.py
decred/dcr/rpc.py
decred/dcr/txscript.py
decred/dcr/vsp.py
decred/dcr/wire/__init__.py
decred/dcr/wire/msgblock.py
decred/dcr/wire/msgtx.py
decred/dcr/wire/wire.py
decred/util/__init__.py
decred/util/chains.py
decred/util/database.py
decred/util/encode.py
decred/util/helpers.py
decred/util/tinyhttp.py
decred/util/ws.py
decred/wallet/__init__.py
decred/wallet/accounts.py
decred/wallet/wallet.py
decred/crypto/secp256k1/field.c
decred/crypto/secp256k1/field.cpython-37m-x86_64-linux-gnu.so
decred-0.1.1.dist-info/WHEEL
decred-0.1.1.dist-info/METADATA
decred-0.1.1.dist-info/RECORD
