Metadata-Version: 2.1
Name: decred
Version: 0.1.1
Summary: A Python 3 Decred toolkit.
Home-page: https://decred.org/
License: ISC
Author: Brian Stafford
Author-email: buck@decred.org
Requires-Python: >=3.6,<4.0
Classifier: Development Status :: 3 - Alpha
Classifier: Intended Audience :: Developers
Classifier: License :: OSI Approved
Classifier: License :: OSI Approved :: ISC License (ISCL)
Classifier: Operating System :: OS Independent
Classifier: Programming Language :: Python :: 3
Classifier: Programming Language :: Python :: 3.6
Classifier: Programming Language :: Python :: 3.7
Classifier: Programming Language :: Python :: 3.8
Classifier: Programming Language :: Python :: 3.9
Classifier: Topic :: Office/Business :: Financial
Requires-Dist: appdirs (>=1.4.3,<2.0.0)
Requires-Dist: base58 (>=2.0.0,<3.0.0)
Requires-Dist: blake256 (>=0.1.1,<0.2.0)
Requires-Dist: pynacl (>=1.3.0,<2.0.0)
Requires-Dist: websocket_client (>=0.57.0,<0.58.0)
Project-URL: Documentation, https://github.com/decred/tinydecred/blob/master/decred
Project-URL: Repository, https://github.com/decred/tinydecred/
